max6675/__init__.py
max6675-0.6.dist-info/METADATA
max6675-0.6.dist-info/WHEEL
max6675-0.6.dist-info/top_level.txt
max6675-0.6.dist-info/RECORD
