Metadata-Version: 2.1
Name: max6675
Version: 0.6
Summary: MAX6675 thermocouple reading with pyfirmata2
Home-page: https://catalyseur.ca/
Author: Francis B. Lavoie
Author-email: francis.b.lavoie@usherbrooke.ca
License: UNKNOWN
Platform: UNKNOWN
Classifier: Programming Language :: Python :: 3
Classifier: License :: OSI Approved :: BSD License
Classifier: Operating System :: OS Independent
